sfis_tools/__init__.py
sfis_tools/__main__.py
sfis_tools/api_client.py
sfis_tools/info.py
sfis_tools/main.py
sfis_tools/models.py
sfis_tools/settings.py
sfis_tools-0.2.0.dist-info/METADATA
sfis_tools-0.2.0.dist-info/WHEEL
sfis_tools-0.2.0.dist-info/entry_points.txt
sfis_tools-0.2.0.dist-info/RECORD
