Metadata-Version: 2.1
Name: sfis-tools
Version: 0.2.0
Summary: 
Author: Erik Hartwig
Author-email: erik.hartwig@gmail.com
Requires-Python: >=3.10,<4.0
Classifier: Programming Language :: Python :: 3
Classifier: Programming Language :: Python :: 3.10
Classifier: Programming Language :: Python :: 3.11
Classifier: Programming Language :: Python :: 3.12
Requires-Dist: keyring (>=25.3.0,<26.0.0)
Requires-Dist: platformdirs (>=4.2.2,<5.0.0)
Requires-Dist: typer[all] (>=0.12.4,<0.13.0)
